geniusbot/__init__.py
geniusbot/geniusbot.py
geniusbot/logger.py
geniusbot/version.py
geniusbot/img/geniusbot.ico
geniusbot/img/geniusbot.png
geniusbot/plugins/__init__.py
geniusbot/plugins/geniusbot_chat_plugin.py
geniusbot/plugins/media_downloader_plugin.py
geniusbot/plugins/media_manager_plugin.py
geniusbot/plugins/report_manager_plugin.py
geniusbot/plugins/repository_manager_plugin.py
geniusbot/plugins/rom_manager_plugin.py
geniusbot/plugins/subshift_plugin.py
geniusbot/plugins/systems_manager_plugin.py
geniusbot/plugins/webarchiver_plugin.py
geniusbot/qt/__init__.py
geniusbot/qt/colors.py
geniusbot/qt/scrollable_widget.py
geniusbot-3.29.6.data/data/geniusbot/geniusbot.ico
geniusbot-3.29.6.data/data/geniusbot/geniusbot.png
geniusbot-3.29.6.dist-info/LICENSE
geniusbot-3.29.6.dist-info/METADATA
geniusbot-3.29.6.dist-info/WHEEL
geniusbot-3.29.6.dist-info/entry_points.txt
geniusbot-3.29.6.dist-info/top_level.txt
geniusbot-3.29.6.dist-info/RECORD
