Metadata-Version: 2.1
Name: geniusbot
Version: 3.29.6
Summary: The Ever-learning and ever-improving tool!
Home-page: https://github.com/Knuckles-Team/geniusbot
Author: Audel Rouhi
Author-email: knucklessg1@gmail.com
License: MIT
Keywords: genius,geniusbot,download,video,subtitle,website,screenshot,media,manage,chatbot,report,profiling,merge
Platform: UNKNOWN
Classifier: Development Status :: 5 - Production/Stable
Classifier: License :: Public Domain
Classifier: Environment :: Console
Classifier: Operating System :: POSIX :: Linux
Classifier: Programming Language :: Python :: 3.8
Classifier: Programming Language :: Python :: 3.9
Classifier: Programming Language :: Python :: 3.10
Classifier: Programming Language :: Python :: 3.11
Classifier: Programming Language :: Python :: 3.12
License-File: LICENSE
Requires-Dist: PyQt6 (>=6.6.1)
Requires-Dist: genius-chatbot (>=1.10.3)
Requires-Dist: systems-manager (>=0.30.2)
Requires-Dist: pypiwin32 ; platform_system == "Windows"
Requires-Dist: winshell (>=0.6) ; platform_system == "Windows"
Provides-Extra: all
Requires-Dist: audio-transcriber ; extra == 'all'
Requires-Dist: media-downloader ; extra == 'all'
Requires-Dist: media-manager ; extra == 'all'
Requires-Dist: report-manager ; extra == 'all'
Requires-Dist: repository-manager ; extra == 'all'
Requires-Dist: rom-manager ; extra == 'all'
Requires-Dist: subshift ; extra == 'all'
Requires-Dist: webarchiver ; extra == 'all'
Provides-Extra: audio-transcriber
Requires-Dist: audio-transcriber ; extra == 'audio-transcriber'
Provides-Extra: media-downloader
Requires-Dist: media-downloader ; extra == 'media-downloader'
Provides-Extra: media-manager
Requires-Dist: media-manager ; extra == 'media-manager'
Provides-Extra: report-manager
Requires-Dist: report-manager ; extra == 'report-manager'
Provides-Extra: repository-manager
Requires-Dist: repository-manager ; extra == 'repository-manager'
Provides-Extra: rom-manager
Requires-Dist: rom-manager ; extra == 'rom-manager'
Provides-Extra: subshift
Requires-Dist: subshift ; extra == 'subshift'
Provides-Extra: webarchiver
Requires-Dist: webarchiver ; extra == 'webarchiver'
